[
  {
    "pollster": "insa",
    "date": "2026-05-15",
    "start": "2026-05-15",
    "end": "2026-05-15",
    "respondents": 1000,
    "party": "cdu",
    "percent": 20,
    "votes": 200,
    "election": "ltw_be"
  },
  {
    "pollster": "insa",
    "date": "2026-05-15",
    "start": "2026-05-15",
    "end": "2026-05-15",
    "respondents": 1000,
    "party": "spd",
    "percent": 16,
    "votes": 160,
    "election": "ltw_be"
  },
  {
    "pollster": "insa",
    "date": "2026-05-15",
    "start": "2026-05-15",
    "end": "2026-05-15",
    "respondents": 1000,
    "party": "greens",
    "percent": 15,
    "votes": 150,
    "election": "ltw_be"
  },
  {
    "pollster": "insa",
    "date": "2026-05-15",
    "start": "2026-05-15",
    "end": "2026-05-15",
    "respondents": 1000,
    "party": "fdp",
    "percent": 4,
    "votes": 40,
    "election": "ltw_be"
  },
  {
    "pollster": "insa",
    "date": "2026-05-15",
    "start": "2026-05-15",
    "end": "2026-05-15",
    "respondents": 1000,
    "party": "left",
    "percent": 15,
    "votes": 150,
    "election": "ltw_be"
  },
  {
    "pollster": "insa",
    "date": "2026-05-15",
    "start": "2026-05-15",
    "end": "2026-05-15",
    "respondents": 1000,
    "party": "afd",
    "percent": 18,
    "votes": 180,
    "election": "ltw_be"
  },
  {
    "pollster": "insa",
    "date": "2026-05-15",
    "start": "2026-05-15",
    "end": "2026-05-15",
    "respondents": 1000,
    "party": "bsw",
    "percent": 4,
    "votes": 40,
    "election": "ltw_be"
  },
  {
    "pollster": "insa",
    "date": "2026-05-15",
    "start": "2026-05-15",
    "end": "2026-05-15",
    "respondents": 1000,
    "party": "others",
    "percent": 8,
    "votes": 80,
    "election": "ltw_be"
  },
  {
    "pollster": "pooled",
    "date": "2026-05-15",
    "start": "2026-04-29",
    "end": "2026-05-15",
    "respondents": 1066.6489,
    "party": "afd",
    "percent": 18,
    "votes": 191.9968,
    "election": "ltw_be"
  },
  {
    "pollster": "pooled",
    "date": "2026-05-15",
    "start": "2026-04-29",
    "end": "2026-05-15",
    "respondents": 1066.6489,
    "party": "bsw",
    "percent": 3.6339,
    "votes": 38.7611,
    "election": "ltw_be"
  },
  {
    "pollster": "pooled",
    "date": "2026-05-15",
    "start": "2026-04-29",
    "end": "2026-05-15",
    "respondents": 1066.6489,
    "party": "cdu",
    "percent": 19.6339,
    "votes": 209.4249,
    "election": "ltw_be"
  },
  {
    "pollster": "pooled",
    "date": "2026-05-15",
    "start": "2026-04-29",
    "end": "2026-05-15",
    "respondents": 1066.6489,
    "party": "fdp",
    "percent": 3.6339,
    "votes": 38.7611,
    "election": "ltw_be"
  },
  {
    "pollster": "pooled",
    "date": "2026-05-15",
    "start": "2026-04-29",
    "end": "2026-05-15",
    "respondents": 1066.6489,
    "party": "greens",
    "percent": 16.0983,
    "votes": 171.7119,
    "election": "ltw_be"
  },
  {
    "pollster": "pooled",
    "date": "2026-05-15",
    "start": "2026-04-29",
    "end": "2026-05-15",
    "respondents": 1066.6489,
    "party": "left",
    "percent": 16.0983,
    "votes": 171.7119,
    "election": "ltw_be"
  },
  {
    "pollster": "pooled",
    "date": "2026-05-15",
    "start": "2026-04-29",
    "end": "2026-05-15",
    "respondents": 1066.6489,
    "party": "others",
    "percent": 7.6339,
    "votes": 81.4271,
    "election": "ltw_be"
  },
  {
    "pollster": "pooled",
    "date": "2026-05-15",
    "start": "2026-04-29",
    "end": "2026-05-15",
    "respondents": 1066.6489,
    "party": "spd",
    "percent": 15.2678,
    "votes": 162.8541,
    "election": "ltw_be"
  },
  {
    "pollster": "infratest",
    "date": "2026-04-29",
    "start": "2026-04-29",
    "end": "2026-04-29",
    "respondents": 1155,
    "party": "cdu",
    "percent": 19,
    "votes": 219.45,
    "election": "ltw_be"
  },
  {
    "pollster": "infratest",
    "date": "2026-04-29",
    "start": "2026-04-29",
    "end": "2026-04-29",
    "respondents": 1155,
    "party": "spd",
    "percent": 14,
    "votes": 161.7,
    "election": "ltw_be"
  },
  {
    "pollster": "infratest",
    "date": "2026-04-29",
    "start": "2026-04-29",
    "end": "2026-04-29",
    "respondents": 1155,
    "party": "greens",
    "percent": 18,
    "votes": 207.9,
    "election": "ltw_be"
  },
  {
    "pollster": "infratest",
    "date": "2026-04-29",
    "start": "2026-04-29",
    "end": "2026-04-29",
    "respondents": 1155,
    "party": "fdp",
    "percent": 3,
    "votes": 34.65,
    "election": "ltw_be"
  },
  {
    "pollster": "infratest",
    "date": "2026-04-29",
    "start": "2026-04-29",
    "end": "2026-04-29",
    "respondents": 1155,
    "party": "left",
    "percent": 18,
    "votes": 207.9,
    "election": "ltw_be"
  },
  {
    "pollster": "infratest",
    "date": "2026-04-29",
    "start": "2026-04-29",
    "end": "2026-04-29",
    "respondents": 1155,
    "party": "afd",
    "percent": 18,
    "votes": 207.9,
    "election": "ltw_be"
  },
  {
    "pollster": "infratest",
    "date": "2026-04-29",
    "start": "2026-04-29",
    "end": "2026-04-29",
    "respondents": 1155,
    "party": "bsw",
    "percent": 3,
    "votes": 34.65,
    "election": "ltw_be"
  },
  {
    "pollster": "infratest",
    "date": "2026-04-29",
    "start": "2026-04-29",
    "end": "2026-04-29",
    "respondents": 1155,
    "party": "others",
    "percent": 7,
    "votes": 80.85,
    "election": "ltw_be"
  },
  {
    "pollster": "pooled",
    "date": "2026-04-29",
    "start": "2026-04-14",
    "end": "2026-04-29",
    "respondents": 1129.7052,
    "party": "afd",
    "percent": 17.6979,
    "votes": 199.9339,
    "election": "ltw_be"
  },
  {
    "pollster": "pooled",
    "date": "2026-04-29",
    "start": "2026-04-14",
    "end": "2026-04-29",
    "respondents": 1129.7052,
    "party": "bsw",
    "percent": 3.3021,
    "votes": 37.3042,
    "election": "ltw_be"
  },
  {
    "pollster": "pooled",
    "date": "2026-04-29",
    "start": "2026-04-14",
    "end": "2026-04-29",
    "respondents": 1129.7052,
    "party": "cdu",
    "percent": 19.6042,
    "votes": 221.47,
    "election": "ltw_be"
  },
  {
    "pollster": "pooled",
    "date": "2026-04-29",
    "start": "2026-04-14",
    "end": "2026-04-29",
    "respondents": 1129.7052,
    "party": "fdp",
    "percent": 3,
    "votes": 33.8912,
    "election": "ltw_be"
  },
  {
    "pollster": "pooled",
    "date": "2026-04-29",
    "start": "2026-04-14",
    "end": "2026-04-29",
    "respondents": 1129.7052,
    "party": "greens",
    "percent": 17.0937,
    "votes": 193.1079,
    "election": "ltw_be"
  },
  {
    "pollster": "pooled",
    "date": "2026-04-29",
    "start": "2026-04-14",
    "end": "2026-04-29",
    "respondents": 1129.7052,
    "party": "left",
    "percent": 17.0937,
    "votes": 193.1079,
    "election": "ltw_be"
  },
  {
    "pollster": "pooled",
    "date": "2026-04-29",
    "start": "2026-04-14",
    "end": "2026-04-29",
    "respondents": 1129.7052,
    "party": "others",
    "percent": 7.3021,
    "votes": 82.4924,
    "election": "ltw_be"
  },
  {
    "pollster": "pooled",
    "date": "2026-04-29",
    "start": "2026-04-14",
    "end": "2026-04-29",
    "respondents": 1129.7052,
    "party": "spd",
    "percent": 14.9063,
    "votes": 168.3977,
    "election": "ltw_be"
  },
  {
    "pollster": "insa",
    "date": "2026-04-14",
    "start": "2026-04-14",
    "end": "2026-04-14",
    "respondents": 1000,
    "party": "cdu",
    "percent": 21,
    "votes": 210,
    "election": "ltw_be"
  },
  {
    "pollster": "insa",
    "date": "2026-04-14",
    "start": "2026-04-14",
    "end": "2026-04-14",
    "respondents": 1000,
    "party": "spd",
    "percent": 17,
    "votes": 170,
    "election": "ltw_be"
  },
  {
    "pollster": "insa",
    "date": "2026-04-14",
    "start": "2026-04-14",
    "end": "2026-04-14",
    "respondents": 1000,
    "party": "greens",
    "percent": 15,
    "votes": 150,
    "election": "ltw_be"
  },
  {
    "pollster": "insa",
    "date": "2026-04-14",
    "start": "2026-04-14",
    "end": "2026-04-14",
    "respondents": 1000,
    "party": "fdp",
    "percent": 3,
    "votes": 30,
    "election": "ltw_be"
  },
  {
    "pollster": "insa",
    "date": "2026-04-14",
    "start": "2026-04-14",
    "end": "2026-04-14",
    "respondents": 1000,
    "party": "left",
    "percent": 15,
    "votes": 150,
    "election": "ltw_be"
  },
  {
    "pollster": "insa",
    "date": "2026-04-14",
    "start": "2026-04-14",
    "end": "2026-04-14",
    "respondents": 1000,
    "party": "afd",
    "percent": 17,
    "votes": 170,
    "election": "ltw_be"
  },
  {
    "pollster": "insa",
    "date": "2026-04-14",
    "start": "2026-04-14",
    "end": "2026-04-14",
    "respondents": 1000,
    "party": "bsw",
    "percent": 4,
    "votes": 40,
    "election": "ltw_be"
  },
  {
    "pollster": "insa",
    "date": "2026-04-14",
    "start": "2026-04-14",
    "end": "2026-04-14",
    "respondents": 1000,
    "party": "others",
    "percent": 8,
    "votes": 80,
    "election": "ltw_be"
  },
  {
    "pollster": "pooled",
    "date": "2026-04-14",
    "start": "2026-04-14",
    "end": "2026-04-14",
    "respondents": 1000,
    "party": "afd",
    "percent": 17,
    "votes": 170,
    "election": "ltw_be"
  },
  {
    "pollster": "pooled",
    "date": "2026-04-14",
    "start": "2026-04-14",
    "end": "2026-04-14",
    "respondents": 1000,
    "party": "bsw",
    "percent": 4,
    "votes": 40,
    "election": "ltw_be"
  },
  {
    "pollster": "pooled",
    "date": "2026-04-14",
    "start": "2026-04-14",
    "end": "2026-04-14",
    "respondents": 1000,
    "party": "cdu",
    "percent": 21,
    "votes": 210,
    "election": "ltw_be"
  },
  {
    "pollster": "pooled",
    "date": "2026-04-14",
    "start": "2026-04-14",
    "end": "2026-04-14",
    "respondents": 1000,
    "party": "fdp",
    "percent": 3,
    "votes": 30,
    "election": "ltw_be"
  },
  {
    "pollster": "pooled",
    "date": "2026-04-14",
    "start": "2026-04-14",
    "end": "2026-04-14",
    "respondents": 1000,
    "party": "greens",
    "percent": 15,
    "votes": 150,
    "election": "ltw_be"
  },
  {
    "pollster": "pooled",
    "date": "2026-04-14",
    "start": "2026-04-14",
    "end": "2026-04-14",
    "respondents": 1000,
    "party": "left",
    "percent": 15,
    "votes": 150,
    "election": "ltw_be"
  },
  {
    "pollster": "pooled",
    "date": "2026-04-14",
    "start": "2026-04-14",
    "end": "2026-04-14",
    "respondents": 1000,
    "party": "others",
    "percent": 8,
    "votes": 80,
    "election": "ltw_be"
  },
  {
    "pollster": "pooled",
    "date": "2026-04-14",
    "start": "2026-04-14",
    "end": "2026-04-14",
    "respondents": 1000,
    "party": "spd",
    "percent": 17,
    "votes": 170,
    "election": "ltw_be"
  },
  {
    "pollster": "insa",
    "date": "2026-02-25",
    "start": "2026-02-25",
    "end": "2026-02-25",
    "respondents": 1000,
    "party": "cdu",
    "percent": 22,
    "votes": 220,
    "election": "ltw_be"
  },
  {
    "pollster": "insa",
    "date": "2026-02-25",
    "start": "2026-02-25",
    "end": "2026-02-25",
    "respondents": 1000,
    "party": "spd",
    "percent": 16,
    "votes": 160,
    "election": "ltw_be"
  },
  {
    "pollster": "insa",
    "date": "2026-02-25",
    "start": "2026-02-25",
    "end": "2026-02-25",
    "respondents": 1000,
    "party": "greens",
    "percent": 15,
    "votes": 150,
    "election": "ltw_be"
  },
  {
    "pollster": "insa",
    "date": "2026-02-25",
    "start": "2026-02-25",
    "end": "2026-02-25",
    "respondents": 1000,
    "party": "fdp",
    "percent": 4,
    "votes": 40,
    "election": "ltw_be"
  },
  {
    "pollster": "insa",
    "date": "2026-02-25",
    "start": "2026-02-25",
    "end": "2026-02-25",
    "respondents": 1000,
    "party": "left",
    "percent": 15,
    "votes": 150,
    "election": "ltw_be"
  },
  {
    "pollster": "insa",
    "date": "2026-02-25",
    "start": "2026-02-25",
    "end": "2026-02-25",
    "respondents": 1000,
    "party": "afd",
    "percent": 17,
    "votes": 170,
    "election": "ltw_be"
  },
  {
    "pollster": "insa",
    "date": "2026-02-25",
    "start": "2026-02-25",
    "end": "2026-02-25",
    "respondents": 1000,
    "party": "bsw",
    "percent": 4,
    "votes": 40,
    "election": "ltw_be"
  },
  {
    "pollster": "insa",
    "date": "2026-02-25",
    "start": "2026-02-25",
    "end": "2026-02-25",
    "respondents": 1000,
    "party": "others",
    "percent": 7,
    "votes": 70,
    "election": "ltw_be"
  },
  {
    "pollster": "pooled",
    "date": "2026-02-25",
    "start": "2026-02-25",
    "end": "2026-02-25",
    "respondents": 1000,
    "party": "afd",
    "percent": 17,
    "votes": 170,
    "election": "ltw_be"
  },
  {
    "pollster": "pooled",
    "date": "2026-02-25",
    "start": "2026-02-25",
    "end": "2026-02-25",
    "respondents": 1000,
    "party": "bsw",
    "percent": 4,
    "votes": 40,
    "election": "ltw_be"
  },
  {
    "pollster": "pooled",
    "date": "2026-02-25",
    "start": "2026-02-25",
    "end": "2026-02-25",
    "respondents": 1000,
    "party": "cdu",
    "percent": 22,
    "votes": 220,
    "election": "ltw_be"
  },
  {
    "pollster": "pooled",
    "date": "2026-02-25",
    "start": "2026-02-25",
    "end": "2026-02-25",
    "respondents": 1000,
    "party": "fdp",
    "percent": 4,
    "votes": 40,
    "election": "ltw_be"
  },
  {
    "pollster": "pooled",
    "date": "2026-02-25",
    "start": "2026-02-25",
    "end": "2026-02-25",
    "respondents": 1000,
    "party": "greens",
    "percent": 15,
    "votes": 150,
    "election": "ltw_be"
  },
  {
    "pollster": "pooled",
    "date": "2026-02-25",
    "start": "2026-02-25",
    "end": "2026-02-25",
    "respondents": 1000,
    "party": "left",
    "percent": 15,
    "votes": 150,
    "election": "ltw_be"
  },
  {
    "pollster": "pooled",
    "date": "2026-02-25",
    "start": "2026-02-25",
    "end": "2026-02-25",
    "respondents": 1000,
    "party": "others",
    "percent": 7,
    "votes": 70,
    "election": "ltw_be"
  },
  {
    "pollster": "pooled",
    "date": "2026-02-25",
    "start": "2026-02-25",
    "end": "2026-02-25",
    "respondents": 1000,
    "party": "spd",
    "percent": 16,
    "votes": 160,
    "election": "ltw_be"
  },
  {
    "pollster": "infratest",
    "date": "2026-01-16",
    "start": "2026-01-16",
    "end": "2026-01-16",
    "respondents": 1173,
    "party": "cdu",
    "percent": 22,
    "votes": 258.06,
    "election": "ltw_be"
  },
  {
    "pollster": "infratest",
    "date": "2026-01-16",
    "start": "2026-01-16",
    "end": "2026-01-16",
    "respondents": 1173,
    "party": "spd",
    "percent": 14,
    "votes": 164.22,
    "election": "ltw_be"
  },
  {
    "pollster": "infratest",
    "date": "2026-01-16",
    "start": "2026-01-16",
    "end": "2026-01-16",
    "respondents": 1173,
    "party": "greens",
    "percent": 16,
    "votes": 187.68,
    "election": "ltw_be"
  },
  {
    "pollster": "infratest",
    "date": "2026-01-16",
    "start": "2026-01-16",
    "end": "2026-01-16",
    "respondents": 1173,
    "party": "left",
    "percent": 18,
    "votes": 211.14,
    "election": "ltw_be"
  },
  {
    "pollster": "infratest",
    "date": "2026-01-16",
    "start": "2026-01-16",
    "end": "2026-01-16",
    "respondents": 1173,
    "party": "afd",
    "percent": 17,
    "votes": 199.41,
    "election": "ltw_be"
  },
  {
    "pollster": "infratest",
    "date": "2026-01-16",
    "start": "2026-01-16",
    "end": "2026-01-16",
    "respondents": 1173,
    "party": "bsw",
    "percent": 3,
    "votes": 35.19,
    "election": "ltw_be"
  },
  {
    "pollster": "infratest",
    "date": "2026-01-16",
    "start": "2026-01-16",
    "end": "2026-01-16",
    "respondents": 1173,
    "party": "others",
    "percent": 10,
    "votes": 117.3,
    "election": "ltw_be"
  },
  {
    "pollster": "pooled",
    "date": "2026-01-16",
    "start": "2026-01-14",
    "end": "2026-01-16",
    "respondents": 1450.2011,
    "party": "afd",
    "percent": 16.5398,
    "votes": 239.8605,
    "election": "ltw_be"
  },
  {
    "pollster": "pooled",
    "date": "2026-01-16",
    "start": "2026-01-14",
    "end": "2026-01-16",
    "respondents": 1450.2011,
    "party": "bsw",
    "percent": 3.4602,
    "votes": 50.1798,
    "election": "ltw_be"
  },
  {
    "pollster": "pooled",
    "date": "2026-01-16",
    "start": "2026-01-14",
    "end": "2026-01-16",
    "respondents": 1450.2011,
    "party": "cdu",
    "percent": 22,
    "votes": 319.0442,
    "election": "ltw_be"
  },
  {
    "pollster": "pooled",
    "date": "2026-01-16",
    "start": "2026-01-14",
    "end": "2026-01-16",
    "respondents": 1450.2011,
    "party": "fdp",
    "percent": 2.9913,
    "votes": 43.3792,
    "election": "ltw_be"
  },
  {
    "pollster": "pooled",
    "date": "2026-01-16",
    "start": "2026-01-14",
    "end": "2026-01-16",
    "respondents": 1450.2011,
    "party": "greens",
    "percent": 15.0796,
    "votes": 218.6847,
    "election": "ltw_be"
  },
  {
    "pollster": "pooled",
    "date": "2026-01-16",
    "start": "2026-01-14",
    "end": "2026-01-16",
    "respondents": 1450.2011,
    "party": "left",
    "percent": 17.5398,
    "votes": 254.3625,
    "election": "ltw_be"
  },
  {
    "pollster": "pooled",
    "date": "2026-01-16",
    "start": "2026-01-14",
    "end": "2026-01-16",
    "respondents": 1450.2011,
    "party": "others",
    "percent": 6.9949,
    "votes": 101.4407,
    "election": "ltw_be"
  },
  {
    "pollster": "pooled",
    "date": "2026-01-16",
    "start": "2026-01-14",
    "end": "2026-01-16",
    "respondents": 1450.2011,
    "party": "spd",
    "percent": 15.3806,
    "votes": 223.0493,
    "election": "ltw_be"
  },
  {
    "pollster": "insa",
    "date": "2026-01-14",
    "start": "2026-01-14",
    "end": "2026-01-14",
    "respondents": 1000,
    "party": "cdu",
    "percent": 22,
    "votes": 220,
    "election": "ltw_be"
  },
  {
    "pollster": "insa",
    "date": "2026-01-14",
    "start": "2026-01-14",
    "end": "2026-01-14",
    "respondents": 1000,
    "party": "spd",
    "percent": 17,
    "votes": 170,
    "election": "ltw_be"
  },
  {
    "pollster": "insa",
    "date": "2026-01-14",
    "start": "2026-01-14",
    "end": "2026-01-14",
    "respondents": 1000,
    "party": "greens",
    "percent": 14,
    "votes": 140,
    "election": "ltw_be"
  },
  {
    "pollster": "insa",
    "date": "2026-01-14",
    "start": "2026-01-14",
    "end": "2026-01-14",
    "respondents": 1000,
    "party": "fdp",
    "percent": 3,
    "votes": 30,
    "election": "ltw_be"
  },
  {
    "pollster": "insa",
    "date": "2026-01-14",
    "start": "2026-01-14",
    "end": "2026-01-14",
    "respondents": 1000,
    "party": "left",
    "percent": 17,
    "votes": 170,
    "election": "ltw_be"
  },
  {
    "pollster": "insa",
    "date": "2026-01-14",
    "start": "2026-01-14",
    "end": "2026-01-14",
    "respondents": 1000,
    "party": "afd",
    "percent": 16,
    "votes": 160,
    "election": "ltw_be"
  },
  {
    "pollster": "insa",
    "date": "2026-01-14",
    "start": "2026-01-14",
    "end": "2026-01-14",
    "respondents": 1000,
    "party": "bsw",
    "percent": 4,
    "votes": 40,
    "election": "ltw_be"
  },
  {
    "pollster": "insa",
    "date": "2026-01-14",
    "start": "2026-01-14",
    "end": "2026-01-14",
    "respondents": 1000,
    "party": "others",
    "percent": 7,
    "votes": 70,
    "election": "ltw_be"
  },
  {
    "pollster": "pooled",
    "date": "2026-01-14",
    "start": "2026-01-14",
    "end": "2026-01-14",
    "respondents": 1000,
    "party": "afd",
    "percent": 16,
    "votes": 160,
    "election": "ltw_be"
  },
  {
    "pollster": "pooled",
    "date": "2026-01-14",
    "start": "2026-01-14",
    "end": "2026-01-14",
    "respondents": 1000,
    "party": "bsw",
    "percent": 4,
    "votes": 40,
    "election": "ltw_be"
  },
  {
    "pollster": "pooled",
    "date": "2026-01-14",
    "start": "2026-01-14",
    "end": "2026-01-14",
    "respondents": 1000,
    "party": "cdu",
    "percent": 22,
    "votes": 220,
    "election": "ltw_be"
  },
  {
    "pollster": "pooled",
    "date": "2026-01-14",
    "start": "2026-01-14",
    "end": "2026-01-14",
    "respondents": 1000,
    "party": "fdp",
    "percent": 3,
    "votes": 30,
    "election": "ltw_be"
  },
  {
    "pollster": "pooled",
    "date": "2026-01-14",
    "start": "2026-01-14",
    "end": "2026-01-14",
    "respondents": 1000,
    "party": "greens",
    "percent": 14,
    "votes": 140,
    "election": "ltw_be"
  },
  {
    "pollster": "pooled",
    "date": "2026-01-14",
    "start": "2026-01-14",
    "end": "2026-01-14",
    "respondents": 1000,
    "party": "left",
    "percent": 17,
    "votes": 170,
    "election": "ltw_be"
  },
  {
    "pollster": "pooled",
    "date": "2026-01-14",
    "start": "2026-01-14",
    "end": "2026-01-14",
    "respondents": 1000,
    "party": "others",
    "percent": 7,
    "votes": 70,
    "election": "ltw_be"
  },
  {
    "pollster": "pooled",
    "date": "2026-01-14",
    "start": "2026-01-14",
    "end": "2026-01-14",
    "respondents": 1000,
    "party": "spd",
    "percent": 17,
    "votes": 170,
    "election": "ltw_be"
  },
  {
    "pollster": "infratest",
    "date": "2025-11-19",
    "start": "2025-11-19",
    "end": "2025-11-19",
    "respondents": 1185,
    "party": "cdu",
    "percent": 22,
    "votes": 260.7,
    "election": "ltw_be"
  },
  {
    "pollster": "infratest",
    "date": "2025-11-19",
    "start": "2025-11-19",
    "end": "2025-11-19",
    "respondents": 1185,
    "party": "spd",
    "percent": 13,
    "votes": 154.05,
    "election": "ltw_be"
  },
  {
    "pollster": "infratest",
    "date": "2025-11-19",
    "start": "2025-11-19",
    "end": "2025-11-19",
    "respondents": 1185,
    "party": "greens",
    "percent": 16,
    "votes": 189.6,
    "election": "ltw_be"
  },
  {
    "pollster": "infratest",
    "date": "2025-11-19",
    "start": "2025-11-19",
    "end": "2025-11-19",
    "respondents": 1185,
    "party": "left",
    "percent": 19,
    "votes": 225.15,
    "election": "ltw_be"
  },
  {
    "pollster": "infratest",
    "date": "2025-11-19",
    "start": "2025-11-19",
    "end": "2025-11-19",
    "respondents": 1185,
    "party": "afd",
    "percent": 16,
    "votes": 189.6,
    "election": "ltw_be"
  },
  {
    "pollster": "infratest",
    "date": "2025-11-19",
    "start": "2025-11-19",
    "end": "2025-11-19",
    "respondents": 1185,
    "party": "bsw",
    "percent": 4,
    "votes": 47.4,
    "election": "ltw_be"
  },
  {
    "pollster": "infratest",
    "date": "2025-11-19",
    "start": "2025-11-19",
    "end": "2025-11-19",
    "respondents": 1185,
    "party": "others",
    "percent": 10,
    "votes": 118.5,
    "election": "ltw_be"
  },
  {
    "pollster": "pooled",
    "date": "2025-11-19",
    "start": "2025-10-28",
    "end": "2025-11-19",
    "respondents": 1154.4779,
    "party": "afd",
    "percent": 15.7033,
    "votes": 181.2907,
    "election": "ltw_be"
  },
  {
    "pollster": "pooled",
    "date": "2025-11-19",
    "start": "2025-10-28",
    "end": "2025-11-19",
    "respondents": 1154.4779,
    "party": "bsw",
    "percent": 4.2967,
    "votes": 49.6049,
    "election": "ltw_be"
  },
  {
    "pollster": "pooled",
    "date": "2025-11-19",
    "start": "2025-10-28",
    "end": "2025-11-19",
    "respondents": 1154.4779,
    "party": "cdu",
    "percent": 22.2967,
    "votes": 257.4109,
    "election": "ltw_be"
  },
  {
    "pollster": "pooled",
    "date": "2025-11-19",
    "start": "2025-10-28",
    "end": "2025-11-19",
    "respondents": 1154.4779,
    "party": "fdp",
    "percent": 3.9763,
    "votes": 45.9051,
    "election": "ltw_be"
  },
  {
    "pollster": "pooled",
    "date": "2025-11-19",
    "start": "2025-10-28",
    "end": "2025-11-19",
    "respondents": 1154.4779,
    "party": "greens",
    "percent": 15.4065,
    "votes": 177.865,
    "election": "ltw_be"
  },
  {
    "pollster": "pooled",
    "date": "2025-11-19",
    "start": "2025-10-28",
    "end": "2025-11-19",
    "respondents": 1154.4779,
    "party": "left",
    "percent": 18.4065,
    "votes": 212.4993,
    "election": "ltw_be"
  },
  {
    "pollster": "pooled",
    "date": "2025-11-19",
    "start": "2025-10-28",
    "end": "2025-11-19",
    "respondents": 1154.4779,
    "party": "others",
    "percent": 5.9941,
    "votes": 69.2002,
    "election": "ltw_be"
  },
  {
    "pollster": "pooled",
    "date": "2025-11-19",
    "start": "2025-10-28",
    "end": "2025-11-19",
    "respondents": 1154.4779,
    "party": "spd",
    "percent": 13.8902,
    "votes": 160.3594,
    "election": "ltw_be"
  },
  {
    "pollster": "insa",
    "date": "2025-10-28",
    "start": "2025-10-28",
    "end": "2025-10-28",
    "respondents": 1000,
    "party": "cdu",
    "percent": 23,
    "votes": 230,
    "election": "ltw_be"
  },
  {
    "pollster": "insa",
    "date": "2025-10-28",
    "start": "2025-10-28",
    "end": "2025-10-28",
    "respondents": 1000,
    "party": "spd",
    "percent": 16,
    "votes": 160,
    "election": "ltw_be"
  },
  {
    "pollster": "insa",
    "date": "2025-10-28",
    "start": "2025-10-28",
    "end": "2025-10-28",
    "respondents": 1000,
    "party": "greens",
    "percent": 14,
    "votes": 140,
    "election": "ltw_be"
  },
  {
    "pollster": "insa",
    "date": "2025-10-28",
    "start": "2025-10-28",
    "end": "2025-10-28",
    "respondents": 1000,
    "party": "fdp",
    "percent": 4,
    "votes": 40,
    "election": "ltw_be"
  },
  {
    "pollster": "insa",
    "date": "2025-10-28",
    "start": "2025-10-28",
    "end": "2025-10-28",
    "respondents": 1000,
    "party": "left",
    "percent": 17,
    "votes": 170,
    "election": "ltw_be"
  },
  {
    "pollster": "insa",
    "date": "2025-10-28",
    "start": "2025-10-28",
    "end": "2025-10-28",
    "respondents": 1000,
    "party": "afd",
    "percent": 15,
    "votes": 150,
    "election": "ltw_be"
  },
  {
    "pollster": "insa",
    "date": "2025-10-28",
    "start": "2025-10-28",
    "end": "2025-10-28",
    "respondents": 1000,
    "party": "bsw",
    "percent": 5,
    "votes": 50,
    "election": "ltw_be"
  },
  {
    "pollster": "insa",
    "date": "2025-10-28",
    "start": "2025-10-28",
    "end": "2025-10-28",
    "respondents": 1000,
    "party": "others",
    "percent": 6,
    "votes": 60,
    "election": "ltw_be"
  },
  {
    "pollster": "pooled",
    "date": "2025-10-28",
    "start": "2025-10-28",
    "end": "2025-10-28",
    "respondents": 1000,
    "party": "afd",
    "percent": 15,
    "votes": 150,
    "election": "ltw_be"
  },
  {
    "pollster": "pooled",
    "date": "2025-10-28",
    "start": "2025-10-28",
    "end": "2025-10-28",
    "respondents": 1000,
    "party": "bsw",
    "percent": 5,
    "votes": 50,
    "election": "ltw_be"
  },
  {
    "pollster": "pooled",
    "date": "2025-10-28",
    "start": "2025-10-28",
    "end": "2025-10-28",
    "respondents": 1000,
    "party": "cdu",
    "percent": 23,
    "votes": 230,
    "election": "ltw_be"
  },
  {
    "pollster": "pooled",
    "date": "2025-10-28",
    "start": "2025-10-28",
    "end": "2025-10-28",
    "respondents": 1000,
    "party": "fdp",
    "percent": 4,
    "votes": 40,
    "election": "ltw_be"
  },
  {
    "pollster": "pooled",
    "date": "2025-10-28",
    "start": "2025-10-28",
    "end": "2025-10-28",
    "respondents": 1000,
    "party": "greens",
    "percent": 14,
    "votes": 140,
    "election": "ltw_be"
  },
  {
    "pollster": "pooled",
    "date": "2025-10-28",
    "start": "2025-10-28",
    "end": "2025-10-28",
    "respondents": 1000,
    "party": "left",
    "percent": 17,
    "votes": 170,
    "election": "ltw_be"
  },
  {
    "pollster": "pooled",
    "date": "2025-10-28",
    "start": "2025-10-28",
    "end": "2025-10-28",
    "respondents": 1000,
    "party": "others",
    "percent": 6,
    "votes": 60,
    "election": "ltw_be"
  },
  {
    "pollster": "pooled",
    "date": "2025-10-28",
    "start": "2025-10-28",
    "end": "2025-10-28",
    "respondents": 1000,
    "party": "spd",
    "percent": 16,
    "votes": 160,
    "election": "ltw_be"
  },
  {
    "pollster": "infratest",
    "date": "2025-06-18",
    "start": "2025-06-18",
    "end": "2025-06-18",
    "respondents": 1148,
    "party": "cdu",
    "percent": 25,
    "votes": 287,
    "election": "ltw_be"
  },
  {
    "pollster": "infratest",
    "date": "2025-06-18",
    "start": "2025-06-18",
    "end": "2025-06-18",
    "respondents": 1148,
    "party": "spd",
    "percent": 14,
    "votes": 160.72,
    "election": "ltw_be"
  },
  {
    "pollster": "infratest",
    "date": "2025-06-18",
    "start": "2025-06-18",
    "end": "2025-06-18",
    "respondents": 1148,
    "party": "greens",
    "percent": 15,
    "votes": 172.2,
    "election": "ltw_be"
  },
  {
    "pollster": "infratest",
    "date": "2025-06-18",
    "start": "2025-06-18",
    "end": "2025-06-18",
    "respondents": 1148,
    "party": "left",
    "percent": 19,
    "votes": 218.12,
    "election": "ltw_be"
  },
  {
    "pollster": "infratest",
    "date": "2025-06-18",
    "start": "2025-06-18",
    "end": "2025-06-18",
    "respondents": 1148,
    "party": "afd",
    "percent": 13,
    "votes": 149.24,
    "election": "ltw_be"
  },
  {
    "pollster": "infratest",
    "date": "2025-06-18",
    "start": "2025-06-18",
    "end": "2025-06-18",
    "respondents": 1148,
    "party": "bsw",
    "percent": 4,
    "votes": 45.92,
    "election": "ltw_be"
  },
  {
    "pollster": "infratest",
    "date": "2025-06-18",
    "start": "2025-06-18",
    "end": "2025-06-18",
    "respondents": 1148,
    "party": "others",
    "percent": 10,
    "votes": 114.8,
    "election": "ltw_be"
  },
  {
    "pollster": "pooled",
    "date": "2025-06-18",
    "start": "2025-05-21",
    "end": "2025-06-18",
    "respondents": 1131.062,
    "party": "afd",
    "percent": 13,
    "votes": 147.0381,
    "election": "ltw_be"
  },
  {
    "pollster": "pooled",
    "date": "2025-06-18",
    "start": "2025-05-21",
    "end": "2025-06-18",
    "respondents": 1131.062,
    "party": "bsw",
    "percent": 4.9102,
    "votes": 55.5373,
    "election": "ltw_be"
  },
  {
    "pollster": "pooled",
    "date": "2025-06-18",
    "start": "2025-05-21",
    "end": "2025-06-18",
    "respondents": 1131.062,
    "party": "cdu",
    "percent": 24.6966,
    "votes": 279.3339,
    "election": "ltw_be"
  },
  {
    "pollster": "pooled",
    "date": "2025-06-18",
    "start": "2025-05-21",
    "end": "2025-06-18",
    "respondents": 1131.062,
    "party": "fdp",
    "percent": 2.9733,
    "votes": 33.6299,
    "election": "ltw_be"
  },
  {
    "pollster": "pooled",
    "date": "2025-06-18",
    "start": "2025-05-21",
    "end": "2025-06-18",
    "respondents": 1131.062,
    "party": "greens",
    "percent": 15,
    "votes": 169.6593,
    "election": "ltw_be"
  },
  {
    "pollster": "pooled",
    "date": "2025-06-18",
    "start": "2025-05-21",
    "end": "2025-06-18",
    "respondents": 1131.062,
    "party": "left",
    "percent": 17.1796,
    "votes": 194.3121,
    "election": "ltw_be"
  },
  {
    "pollster": "pooled",
    "date": "2025-06-18",
    "start": "2025-05-21",
    "end": "2025-06-18",
    "respondents": 1131.062,
    "party": "others",
    "percent": 7.2816,
    "votes": 82.3589,
    "election": "ltw_be"
  },
  {
    "pollster": "pooled",
    "date": "2025-06-18",
    "start": "2025-05-21",
    "end": "2025-06-18",
    "respondents": 1131.062,
    "party": "spd",
    "percent": 14.9102,
    "votes": 168.6435,
    "election": "ltw_be"
  },
  {
    "pollster": "insa",
    "date": "2025-05-21",
    "start": "2025-05-21",
    "end": "2025-05-21",
    "respondents": 1000,
    "party": "cdu",
    "percent": 24,
    "votes": 240,
    "election": "ltw_be"
  },
  {
    "pollster": "insa",
    "date": "2025-05-21",
    "start": "2025-05-21",
    "end": "2025-05-21",
    "respondents": 1000,
    "party": "spd",
    "percent": 17,
    "votes": 170,
    "election": "ltw_be"
  },
  {
    "pollster": "insa",
    "date": "2025-05-21",
    "start": "2025-05-21",
    "end": "2025-05-21",
    "respondents": 1000,
    "party": "greens",
    "percent": 15,
    "votes": 150,
    "election": "ltw_be"
  },
  {
    "pollster": "insa",
    "date": "2025-05-21",
    "start": "2025-05-21",
    "end": "2025-05-21",
    "respondents": 1000,
    "party": "fdp",
    "percent": 3,
    "votes": 30,
    "election": "ltw_be"
  },
  {
    "pollster": "insa",
    "date": "2025-05-21",
    "start": "2025-05-21",
    "end": "2025-05-21",
    "respondents": 1000,
    "party": "left",
    "percent": 13,
    "votes": 130,
    "election": "ltw_be"
  },
  {
    "pollster": "insa",
    "date": "2025-05-21",
    "start": "2025-05-21",
    "end": "2025-05-21",
    "respondents": 1000,
    "party": "afd",
    "percent": 13,
    "votes": 130,
    "election": "ltw_be"
  },
  {
    "pollster": "insa",
    "date": "2025-05-21",
    "start": "2025-05-21",
    "end": "2025-05-21",
    "respondents": 1000,
    "party": "bsw",
    "percent": 7,
    "votes": 70,
    "election": "ltw_be"
  },
  {
    "pollster": "insa",
    "date": "2025-05-21",
    "start": "2025-05-21",
    "end": "2025-05-21",
    "respondents": 1000,
    "party": "others",
    "percent": 8,
    "votes": 80,
    "election": "ltw_be"
  },
  {
    "pollster": "pooled",
    "date": "2025-05-21",
    "start": "2025-05-21",
    "end": "2025-05-21",
    "respondents": 1000,
    "party": "afd",
    "percent": 13,
    "votes": 130,
    "election": "ltw_be"
  },
  {
    "pollster": "pooled",
    "date": "2025-05-21",
    "start": "2025-05-21",
    "end": "2025-05-21",
    "respondents": 1000,
    "party": "bsw",
    "percent": 7,
    "votes": 70,
    "election": "ltw_be"
  },
  {
    "pollster": "pooled",
    "date": "2025-05-21",
    "start": "2025-05-21",
    "end": "2025-05-21",
    "respondents": 1000,
    "party": "cdu",
    "percent": 24,
    "votes": 240,
    "election": "ltw_be"
  },
  {
    "pollster": "pooled",
    "date": "2025-05-21",
    "start": "2025-05-21",
    "end": "2025-05-21",
    "respondents": 1000,
    "party": "fdp",
    "percent": 3,
    "votes": 30,
    "election": "ltw_be"
  },
  {
    "pollster": "pooled",
    "date": "2025-05-21",
    "start": "2025-05-21",
    "end": "2025-05-21",
    "respondents": 1000,
    "party": "greens",
    "percent": 15,
    "votes": 150,
    "election": "ltw_be"
  },
  {
    "pollster": "pooled",
    "date": "2025-05-21",
    "start": "2025-05-21",
    "end": "2025-05-21",
    "respondents": 1000,
    "party": "left",
    "percent": 13,
    "votes": 130,
    "election": "ltw_be"
  },
  {
    "pollster": "pooled",
    "date": "2025-05-21",
    "start": "2025-05-21",
    "end": "2025-05-21",
    "respondents": 1000,
    "party": "others",
    "percent": 8,
    "votes": 80,
    "election": "ltw_be"
  },
  {
    "pollster": "pooled",
    "date": "2025-05-21",
    "start": "2025-05-21",
    "end": "2025-05-21",
    "respondents": 1000,
    "party": "spd",
    "percent": 17,
    "votes": 170,
    "election": "ltw_be"
  }
]
